setup.py
NiceCoding/PassworkCreate.py
NiceCoding/__init__.py
PassworkCreate.egg-info/PKG-INFO
PassworkCreate.egg-info/SOURCES.txt
PassworkCreate.egg-info/dependency_links.txt
PassworkCreate.egg-info/requires.txt
PassworkCreate.egg-info/top_level.txt