Metadata-Version: 2.1
Name: PassworkCreate
Version: 0.0.1
Summary: My package TEST
Home-page: https://github.com/your_username/mypackage
Author: Mo Chang Woo
Author-email: at25time@gmail.com
License: MIT
